README
setup.py
src/r53/__init__.py
src/r53/r53.py
src/r53/r53_test.py
src/r53.egg-info/PKG-INFO
src/r53.egg-info/SOURCES.txt
src/r53.egg-info/dependency_links.txt
src/r53.egg-info/entry_points.txt
src/r53.egg-info/not-zip-safe
src/r53.egg-info/requires.txt
src/r53.egg-info/top_level.txt