Metadata-Version: 1.0
Name: r53
Version: 0.4
Summary: Command line script to synchronize Amazon Route53 DNS data.
Home-page: UNKNOWN
Author: UNKNOWN
Author-email: UNKNOWN
License: UNKNOWN
Platform: UNKNOWN
